README.md
puid.py
setup.cfg
setup.py
puid.egg-info/PKG-INFO
puid.egg-info/SOURCES.txt
puid.egg-info/dependency_links.txt
puid.egg-info/entry_points.txt
puid.egg-info/requires.txt
puid.egg-info/top_level.txt