Metadata-Version: 2.1
Name: puid
Version: 0.0.5
Summary: Lookup a PRONOM Unique Identifier for a file.
Home-page: https://github.com/edsu/puid
Author: Ed Summers
Author-email: ehs@pobox.com
License: UNKNOWN
Platform: UNKNOWN
